odoo9_addon_l10n_ch_hr_payroll-9.0.1.4.0-py2.7-nspkg.pth
odoo9_addon_l10n_ch_hr_payroll-9.0.1.4.0.dist-info/DESCRIPTION.rst
odoo9_addon_l10n_ch_hr_payroll-9.0.1.4.0.dist-info/METADATA
odoo9_addon_l10n_ch_hr_payroll-9.0.1.4.0.dist-info/RECORD
odoo9_addon_l10n_ch_hr_payroll-9.0.1.4.0.dist-info/WHEEL
odoo9_addon_l10n_ch_hr_payroll-9.0.1.4.0.dist-info/metadata.json
odoo9_addon_l10n_ch_hr_payroll-9.0.1.4.0.dist-info/namespace_packages.txt
odoo9_addon_l10n_ch_hr_payroll-9.0.1.4.0.dist-info/top_level.txt
odoo_addons/l10n_ch_hr_payroll/README.rst
odoo_addons/l10n_ch_hr_payroll/__init__.py
odoo_addons/l10n_ch_hr_payroll/__openerp__.py
odoo_addons/l10n_ch_hr_payroll/data/hr.salary.rule.category.xml
odoo_addons/l10n_ch_hr_payroll/data/hr.salary.rule.xml
odoo_addons/l10n_ch_hr_payroll/i18n/ca.po
odoo_addons/l10n_ch_hr_payroll/i18n/de.po
odoo_addons/l10n_ch_hr_payroll/i18n/fr.po
odoo_addons/l10n_ch_hr_payroll/i18n/it.po
odoo_addons/l10n_ch_hr_payroll/i18n/nb_NO.po
odoo_addons/l10n_ch_hr_payroll/i18n/nl.po
odoo_addons/l10n_ch_hr_payroll/i18n/zh_CN.po
odoo_addons/l10n_ch_hr_payroll/migrations/8.0.1.0.8/pre-update-ir_model_data.py
odoo_addons/l10n_ch_hr_payroll/models/__init__.py
odoo_addons/l10n_ch_hr_payroll/models/hr_contract.py
odoo_addons/l10n_ch_hr_payroll/models/hr_employee.py
odoo_addons/l10n_ch_hr_payroll/models/hr_salary_rule.py
odoo_addons/l10n_ch_hr_payroll/models/hr_salary_rule_category.py
odoo_addons/l10n_ch_hr_payroll/static/description/icon.png
odoo_addons/l10n_ch_hr_payroll/views/hr_contract_view.xml
odoo_addons/l10n_ch_hr_payroll/views/hr_employee_view.xml
