Metadata-Version: 2.0
Name: odoo9-addon-l10n-ch-hr-payroll
Version: 9.0.1.4.0
Summary: Switzerland Payroll Rules
Home-page: http://open-net.ch
Author: Open Net Sàrl,Odoo Community Association (OCA)
Author-email: support@odoo-community.org
License: AGPL-3
Platform: UNKNOWN
Classifier: Programming Language :: Python
Classifier: Framework :: Odoo
Classifier: License :: OSI Approved :: GNU Affero General Public License v3
Requires-Python: ~=2.7
Requires-Dist: odoo (<9.1a,>=9.0a)
